odoo/addons/stock_picking_invoice_link/README.rst
odoo/addons/stock_picking_invoice_link/__init__.py
odoo/addons/stock_picking_invoice_link/__manifest__.py
odoo/addons/stock_picking_invoice_link/i18n/ca.po
odoo/addons/stock_picking_invoice_link/i18n/de.po
odoo/addons/stock_picking_invoice_link/i18n/es.po
odoo/addons/stock_picking_invoice_link/i18n/es_MX.po
odoo/addons/stock_picking_invoice_link/i18n/fi.po
odoo/addons/stock_picking_invoice_link/i18n/fr.po
odoo/addons/stock_picking_invoice_link/i18n/hr.po
odoo/addons/stock_picking_invoice_link/i18n/it.po
odoo/addons/stock_picking_invoice_link/i18n/nl_NL.po
odoo/addons/stock_picking_invoice_link/i18n/pt.po
odoo/addons/stock_picking_invoice_link/i18n/pt_BR.po
odoo/addons/stock_picking_invoice_link/i18n/sl.po
odoo/addons/stock_picking_invoice_link/i18n/stock_picking_invoice_link.pot
odoo/addons/stock_picking_invoice_link/i18n/tr.po
odoo/addons/stock_picking_invoice_link/i18n/tr_TR.po
odoo/addons/stock_picking_invoice_link/migrations/12.0.2.0.0/post-migrate.py
odoo/addons/stock_picking_invoice_link/models/__init__.py
odoo/addons/stock_picking_invoice_link/models/account_invoice.py
odoo/addons/stock_picking_invoice_link/models/sale_order.py
odoo/addons/stock_picking_invoice_link/models/stock_move.py
odoo/addons/stock_picking_invoice_link/models/stock_picking.py
odoo/addons/stock_picking_invoice_link/readme/CONTRIBUTORS.rst
odoo/addons/stock_picking_invoice_link/readme/DESCRIPTION.rst
odoo/addons/stock_picking_invoice_link/readme/USAGE.rst
odoo/addons/stock_picking_invoice_link/static/description/icon.png
odoo/addons/stock_picking_invoice_link/static/description/index.html
odoo/addons/stock_picking_invoice_link/tests/__init__.py
odoo/addons/stock_picking_invoice_link/tests/test_stock_picking_invoice_link.py
odoo/addons/stock_picking_invoice_link/views/account_invoice_view.xml
odoo/addons/stock_picking_invoice_link/views/stock_view.xml
odoo12_addon_stock_picking_invoice_link-12.0.2.0.2.dist-info/METADATA
odoo12_addon_stock_picking_invoice_link-12.0.2.0.2.dist-info/WHEEL
odoo12_addon_stock_picking_invoice_link-12.0.2.0.2.dist-info/top_level.txt
odoo12_addon_stock_picking_invoice_link-12.0.2.0.2.dist-info/RECORD
